{
    "__comment": "Made with TheDestruc7i0n's advancements generator: https://advancements.thedestruc7i0n.ca",
    "criteria": {
        "caoBlocks": {
            "trigger": "minecraft:impossible"
        }
    },
    "display": {
        "announce_to_chat": false,
        "description": "In a game about mining, how much is too much?",
        "frame": "goal",
        "hidden": false,
        "icon": {
            "item": "minecraft:diamond_pickaxe"
        },
        "show_toast": false,
        "title": "Mining"
    },
    "parent": "elkia:caochallenges/root"
}