{
    "__comment": "Made with TheDestruc7i0n's advancements generator: https://advancements.thedestruc7i0n.ca",
    "display": {
        "title": "Withers? Pfft. (64)",
        "description": "Good luck with this one.",
        "icon": {
            "item": "minecraft:beacon"
        },
        "frame": "challenge",
        "show_toast": true,
        "announce_to_chat": true,
        "hidden": false
    },
    "criteria": {
        "otherBeacons": {
            "trigger": "minecraft:inventory_changed",
            "conditions": {
                "items": [
                    {
                        "item": "minecraft:beacon",
                        "count": {
                            "min": 64,
                            "max": 64
                        }
                    }
                ]
            }
        }
    },
    "parent": "elkia:caochallenges/caoother"
}